[
  {
    "slug": "filters",
    "title": "Best Aquarium Filters in 2025: Complete Buyer's Guide",
    "category": "filter",
    "products": [
      {
        "slug": "aquaclear-50",
        "name": "AquaClear 50 (HOB Filter)",
        "brand": "AquaClear",
        "category": "filter",
        "subcategory": "hob",
        "price": {
          "min": 30,
          "max": 45
        },
        "rating": 4.8,
        "tankSizeRange": {
          "min": 20,
          "max": 50
        },
        "pros": [
          "Customizable media baskets",
          "Quiet operation",
          "Adjustable flow rate",
          "Excellent biological filtration",
          "Easy to maintain",
          "Industry standard for decades"
        ],
        "cons": [
          "Impeller can rattle over time",
          "Not self-priming after power outage",
          "Takes up back-of-tank space"
        ],
        "bestFor": "Best overall HOB filter for 20\u201350 gallon tanks",
        "affiliateUrl": "",
        "imageUrl": "/images/equipment/placeholder.jpg",
        "description": "The AquaClear 50 is the gold standard hang-on-back filter. Its customizable 3-stage media system (foam, carbon, BioMax) provides exceptional biological, chemical, and mechanical filtration. The adjustable flow control lets you dial in the perfect current for any setup \u2014 from gentle betta tanks to moderate community aquariums.",
        "metaTitle": "AquaClear 50 Review",
        "metaDescription": "AquaClear 50 HOB filter review."
      },
      {
        "slug": "fluval-307",
        "name": "Fluval 307 (Canister Filter)",
        "brand": "Fluval",
        "category": "filter",
        "subcategory": "canister",
        "price": {
          "min": 130,
          "max": 180
        },
        "rating": 4.7,
        "tankSizeRange": {
          "min": 40,
          "max": 70
        },
        "pros": [
          "Superior filtration capacity",
          "Whisper quiet",
          "Self-priming",
          "Large media baskets",
          "Clean look (hidden below tank)",
          "Spray bar for even flow distribution"
        ],
        "cons": [
          "Higher upfront cost",
          "More complex maintenance",
          "Hoses can be stiff initially"
        ],
        "bestFor": "Best canister filter for 40\u201370 gallon planted and community tanks",
        "affiliateUrl": "",
        "imageUrl": "/images/equipment/placeholder.jpg",
        "description": "The Fluval 307 is a premium canister filter that sits below your tank inside the cabinet, providing powerful multi-stage filtration with zero visible equipment in the tank. Its large media baskets accommodate diverse filter media configurations, and the self-priming system eliminates the need for manual siphoning during maintenance.",
        "metaTitle": "Fluval 307 Review",
        "metaDescription": "Fluval 307 canister filter review."
      },
      {
        "slug": "aqueon-quietflow-10",
        "name": "Aqueon QuietFlow 10 (HOB Filter)",
        "brand": "Aqueon",
        "category": "filter",
        "subcategory": "hob",
        "price": {
          "min": 15,
          "max": 25
        },
        "rating": 4.3,
        "tankSizeRange": {
          "min": 5,
          "max": 20
        },
        "pros": [
          "Very affordable",
          "Self-priming",
          "Quiet for its price",
          "Widely available",
          "Good starter filter"
        ],
        "cons": [
          "Uses proprietary cartridges (ongoing cost)",
          "Less customizable than AquaClear",
          "Cartridge replacement kills beneficial bacteria"
        ],
        "bestFor": "Best budget HOB filter for beginners with 10\u201320 gallon tanks",
        "affiliateUrl": "",
        "imageUrl": "/images/equipment/placeholder.jpg",
        "description": "The Aqueon QuietFlow 10 is an affordable, reliable HOB filter that comes included in many starter kits. While it uses proprietary replacement cartridges (which experienced hobbyists often modify), it provides adequate filtration for small community tanks and is an excellent entry point for beginners.",
        "metaTitle": "Aqueon QuietFlow 10 Review",
        "metaDescription": "Aqueon QuietFlow 10 HOB filter review."
      },
      {
        "slug": "hikari-bacto-surge-sponge",
        "name": "Hikari Bacto-Surge Sponge Filter",
        "brand": "Hikari",
        "category": "filter",
        "subcategory": "sponge",
        "price": {
          "min": 5,
          "max": 12
        },
        "rating": 4.6,
        "tankSizeRange": {
          "min": 5,
          "max": 40
        },
        "pros": [
          "Ultra cheap",
          "Excellent biological filtration",
          "Gentle flow (safe for fry/shrimp)",
          "No moving parts to fail",
          "Easy to maintain",
          "Pairs with any air pump"
        ],
        "cons": [
          "Requires separate air pump",
          "Not the most attractive in-tank",
          "Limited mechanical filtration"
        ],
        "bestFor": "Best sponge filter for breeding tanks, shrimp tanks, and hospital tanks",
        "affiliateUrl": "",
        "imageUrl": "/images/equipment/placeholder.jpg",
        "description": "Sponge filters are the unsung heroes of the aquarium hobby. Powered by a simple air pump, they provide outstanding biological filtration with gentle, shrimp-safe water flow. The Hikari Bacto-Surge is among the best, with a dual-sponge design that allows you to alternate cleaning (maintaining bacterial colonies) and a weighted base that stays put.",
        "metaTitle": "Hikari Bacto-Surge Sponge Filter Review",
        "metaDescription": "Hikari sponge filter review."
      },
      {
        "slug": "fluval-fx4",
        "name": "Fluval FX4 (Large Canister Filter)",
        "brand": "Fluval",
        "category": "filter",
        "subcategory": "canister",
        "price": {
          "min": 220,
          "max": 300
        },
        "rating": 4.8,
        "tankSizeRange": {
          "min": 55,
          "max": 250
        },
        "pros": [
          "Massive filtration capacity (700 GPH)",
          "Self-priming with smart pump",
          "Built-in drain valve for easy maintenance",
          "Multi-stage media system",
          "Handles the messiest fish",
          "Extremely reliable long-term"
        ],
        "cons": [
          "Expensive",
          "Large physical footprint",
          "Overkill for small tanks",
          "Heavy when full"
        ],
        "bestFor": "Best high-capacity filter for 55+ gallon tanks, oscars, and large cichlid setups",
        "affiliateUrl": "",
        "imageUrl": "/images/equipment/placeholder.jpg",
        "description": "The Fluval FX4 is a powerhouse canister filter designed for large aquariums with heavy bioloads. With 700 GPH flow rate and massive media capacity, it handles the waste output of messy fish like oscars, large cichlids, and heavily stocked community tanks. The built-in drain valve and self-priming smart pump make maintenance surprisingly manageable despite its size.",
        "metaTitle": "Fluval FX4 Review",
        "metaDescription": "Fluval FX4 canister filter review."
      },
      {
        "slug": "fluval-spec-built-in",
        "name": "Fluval Spec V Built-In Filter",
        "brand": "Fluval",
        "category": "filter",
        "subcategory": "internal",
        "price": {
          "min": 80,
          "max": 100
        },
        "rating": 4.5,
        "tankSizeRange": {
          "min": 5,
          "max": 5
        },
        "pros": [
          "Integrated design (no visible equipment)",
          "3-stage filtration in tiny package",
          "Customizable media chamber",
          "Elegant, modern look",
          "Adjustable output nozzle"
        ],
        "cons": [
          "Only works with Fluval Spec tank",
          "Limited to 5 gallons",
          "Replacement pump can be pricey"
        ],
        "bestFor": "Best all-in-one nano tank filter for betta fish and shrimp",
        "affiliateUrl": "",
        "imageUrl": "/images/equipment/placeholder.jpg",
        "description": "The Fluval Spec V's built-in filtration system is a masterclass in nano tank engineering. The rear chamber houses 3 stages of filtration (mechanical, chemical, biological) hidden behind a black panel, keeping the main tank area clean and uncluttered. The adjustable output nozzle lets you control flow \u2014 perfect for bettas that prefer gentle current.",
        "metaTitle": "Fluval Spec V Filter Review",
        "metaDescription": "Fluval Spec V built-in filter review."
      }
    ],
    "introduction": "<h2 id=\"why-filters-matter\">Why Every Aquarium Needs a Filter</h2>\n<p>A filter is the single most critical piece of equipment in any aquarium \u2014 more important than lights, heaters, or decorations. Without filtration, toxic ammonia from fish waste accumulates rapidly, poisoning your fish within days. A good filter performs three essential functions:</p>\n<ul>\n<li><strong>Biological filtration:</strong> Beneficial bacteria colonize filter media and convert toxic ammonia \u2192 nitrite \u2192 less-toxic nitrate. This is the <a href=\"/water-chemistry/how-to-cycle-fish-tank\">nitrogen cycle</a> \u2014 the foundation of successful fishkeeping.</li>\n<li><strong>Mechanical filtration:</strong> Physical media (sponges, floss, foam) trap particulate waste, uneaten food, and debris, keeping water visually clear.</li>\n<li><strong>Chemical filtration:</strong> Activated carbon, Purigen, or other chemical media remove dissolved organic compounds, odors, discoloration, and medications.</li>\n</ul>\n<p>The filter you choose depends on your <a href=\"/tank-sizes\">tank size</a>, the species you keep (some <a href=\"/fish/betta-fish\">bettas</a> need gentle flow, while <a href=\"/fish/oscar-fish\">oscars</a> need heavy-duty filtration), and your budget.</p>\n\n<h2 id=\"filter-types\">Types of Aquarium Filters</h2>\n\n<h3 id=\"hob-filters\">Hang-On-Back (HOB) Filters</h3>\n<p>HOB filters clip onto the back rim of your tank, drawing water up through an intake tube, passing it through media, and returning it via a waterfall-style spillway. They're the most popular filter type for tanks from <a href=\"/tank-sizes/10-gallon-fish-tank\">10 gallons</a> to <a href=\"/tank-sizes/40-gallon-fish-tank\">40 gallons</a>.</p>\n<p><strong>Best for:</strong> Most community tanks, beginners, and anyone wanting easy maintenance. The AquaClear line is the gold standard \u2014 their customizable media baskets (foam \u2192 carbon \u2192 BioMax) provide superior filtration compared to competitors that use disposable cartridges.</p>\n<p><strong>Flow rate rule:</strong> Choose a HOB rated for 4\u20136\u00d7 your tank volume per hour. For a <a href=\"/tank-sizes/20-gallon-fish-tank\">20 gallon tank</a>, that means an 80\u2013120 GPH filter (like the AquaClear 30 or 50).</p>\n\n<h3 id=\"canister-filters\">Canister Filters</h3>\n<p>Canister filters sit below the tank (usually inside the cabinet) and pump water through sealed canisters filled with multiple layers of media. They're the preferred choice for tanks <a href=\"/tank-sizes/40-gallon-fish-tank\">40 gallons</a> and above.</p>\n<p><strong>Advantages over HOBs:</strong> More media capacity (better filtration), hidden from view (cleaner aesthetic), quieter operation, spray bar option for planted tanks (even flow distribution). Canister filters are virtually required for <a href=\"/tank-sizes/55-gallon-fish-tank\">55 gallon</a> and <a href=\"/tank-sizes/75-gallon-fish-tank\">75 gallon+</a> setups.</p>\n<p><strong>Best for:</strong> Planted aquascapes (no visual clutter), large tanks, messy fish (<a href=\"/fish/goldfish\">goldfish</a>, <a href=\"/fish/oscar-fish\">oscars</a>), and aquarists who want the best filtration possible.</p>\n\n<h3 id=\"sponge-filters\">Sponge Filters</h3>\n<p>Sponge filters are simple, cheap, and incredibly effective. An air pump pushes air through a tube inside a sponge \u2014 this draws water through the sponge (mechanical filtration) while the sponge's massive surface area hosts beneficial bacteria (biological filtration).</p>\n<p><strong>Best for:</strong> Breeding tanks (<a href=\"/fish/cherry-shrimp\">shrimp</a> and fry won't get sucked in), <a href=\"/tank-sizes/5-gallon-fish-tank\">nano tanks</a>, hospital/quarantine tanks, and as supplemental filtration in larger setups. Many serious breeders use nothing but sponge filters.</p>\n\n<h3 id=\"internal-filters\">Internal/Submersible Filters</h3>\n<p>Internal filters sit fully submerged inside the tank. They're compact and work well for nano tanks where a HOB doesn't fit or isn't practical.</p>\n<p><strong>Best for:</strong> Nano tanks under 10 gallons, turtle tanks, and setups where a HOB or canister isn't practical.</p>\n\n<h2 id=\"filter-by-tank-size\">Which Filter for Your Tank Size?</h2>\n<ul>\n<li><strong><a href=\"/tank-sizes/3-gallon-fish-tank\">3\u20135 gallons</a>:</strong> Small sponge filter or nano internal filter. Gentle flow is critical for <a href=\"/fish/betta-fish\">bettas</a> and <a href=\"/fish/cherry-shrimp\">shrimp</a>.</li>\n<li><strong><a href=\"/tank-sizes/10-gallon-fish-tank\">10 gallons</a>:</strong> AquaClear 20 or Aqueon QuietFlow 10. A sponge filter also works great here.</li>\n<li><strong><a href=\"/tank-sizes/20-gallon-fish-tank\">20 gallons</a>:</strong> AquaClear 30 or 50. Upgrade to canister (Fluval 107) if you want a cleaner look.</li>\n<li><strong><a href=\"/tank-sizes/29-gallon-fish-tank\">29\u201330 gallons</a>:</strong> AquaClear 50 or Fluval 207 canister.</li>\n<li><strong><a href=\"/tank-sizes/40-gallon-fish-tank\">40 gallons</a>:</strong> Canister filter recommended (Fluval 207/307). AquaClear 70 as HOB alternative.</li>\n<li><strong><a href=\"/tank-sizes/55-gallon-fish-tank\">55 gallons</a>:</strong> Fluval 307 or dual filtration. For messy fish, Fluval FX4.</li>\n<li><strong><a href=\"/tank-sizes/75-gallon-fish-tank\">75+ gallons</a>:</strong> Fluval FX4 or dual canisters. Sump system for ultimate filtration.</li>\n<li><strong><a href=\"/tank-sizes/125-gallon-fish-tank\">125+ gallons</a>:</strong> Fluval FX6 or sump. Dual canisters minimum for heavy bioloads.</li>\n</ul>\n\n<h2 id=\"filter-media\">Understanding Filter Media</h2>\n<p>The filter is just a box that holds water \u2014 it's the <strong>media inside</strong> that does the actual work. Understanding media types lets you optimize any filter:</p>\n<ul>\n<li><strong>Coarse sponge/foam:</strong> First stage. Catches large particles. Rinse in old tank water (never tap water \u2014 chlorine kills bacteria) every 2\u20134 weeks.</li>\n<li><strong>Fine filter floss/polishing pad:</strong> Catches fine particles for crystal-clear water. Replace monthly.</li>\n<li><strong>Biological media (BioMax, Matrix, ceramic rings, lava rock):</strong> The most critical media. Provides surface area for beneficial bacteria. <strong>Never replace all bio-media at once</strong> \u2014 you'll crash your cycle. Rinse gently in old tank water and only replace 1/3 at a time if needed.</li>\n<li><strong>Activated carbon:</strong> Removes odors, discoloration, and dissolved organics. Replace monthly. <strong>Remove during medication</strong> \u2014 carbon absorbs medications before they can work.</li>\n<li><strong>Purigen (Seachem):</strong> Premium chemical media that removes organic waste and keeps water polished. Rechargeable with bleach \u2014 lasts for years.</li>\n</ul>\n\n<h2 id=\"filter-maintenance\">Filter Maintenance Schedule</h2>\n<p>The #1 rule of filter maintenance: <strong>never rinse filter media in tap water.</strong> Chlorine in tap water kills the beneficial bacteria that make your filter work. Always rinse in old tank water removed during water changes.</p>\n<ul>\n<li><strong>Every 2\u20134 weeks:</strong> Rinse mechanical media (sponges, foam) in removed tank water. Replace filter floss if clogged.</li>\n<li><strong>Monthly:</strong> Replace activated carbon. Check impeller for debris.</li>\n<li><strong>Every 3\u20136 months:</strong> Gently rinse biological media in old tank water. Only if flow is noticeably reduced.</li>\n<li><strong>Never:</strong> Replace all filter media at once. Always stagger replacements to preserve bacterial colonies.</li>\n</ul>\n\n<h2 id=\"planted-tank-filters\">Best Filters for Planted Tanks</h2>\n<p>Planted aquariums have specific filtration needs. CO2 injection works best when surface agitation is minimized (agitation off-gases CO2), but good water circulation is still important to distribute nutrients and CO2 throughout the tank.</p>\n<p>For planted tanks with <a href=\"/plants/monte-carlo\">carpet plants</a>, <a href=\"/plants/rotala-rotundifolia\">stem plants</a>, and <a href=\"/plants/java-fern\">epiphytes</a>:</p>\n<ul>\n<li><strong>Canister filters with spray bars</strong> are ideal \u2014 the spray bar can be positioned below the water line to provide circulation without surface agitation.</li>\n<li><strong>Inline CO2 diffusers</strong> can be connected to canister filter tubing for the most efficient CO2 dissolution.</li>\n<li><strong>Avoid strong HOB filters</strong> that create excessive surface turbulence \u2014 this wastes CO2.</li>\n<li>A glass lily pipe set (inflow + outflow) replaces standard canister tubing for a clean, aquascaping-grade look.</li>\n</ul>\n\n<h2 id=\"common-filter-problems\">Common Filter Problems & Fixes</h2>\n<ul>\n<li><strong>Filter not starting after power outage:</strong> HOB filters often lose their prime. Pour tank water into the filter box to re-prime, then plug in. Canister filters with self-priming (like Fluval series) restart automatically.</li>\n<li><strong>Rattling/vibrating noise:</strong> Usually the impeller. Remove, clean, and check for damage. Replace impeller if worn \u2014 they're inexpensive.</li>\n<li><strong>Reduced flow:</strong> Media is clogged. Rinse mechanical media and check intake tube for blockage.</li>\n<li><strong>Filter too strong for betta:</strong> Baffle the outflow with a filter sponge, or switch to a sponge filter. <a href=\"/fish/betta-fish\">Bettas</a> need gentle current due to their long fins.</li>\n<li><strong>Micro-bubbles in water:</strong> Air trapped in canister hoses. Gently rock the canister to release trapped air. Usually resolves within 24 hours.</li>\n</ul>\n\n<h2 id=\"faq\">Frequently Asked Questions</h2>\n<h3>How often should I clean my aquarium filter?</h3>\n<p>Rinse mechanical media every 2\u20134 weeks in old tank water. Biological media should be rinsed gently only every 3\u20136 months if flow is reduced. Never clean everything at once \u2014 stagger maintenance to preserve bacterial colonies.</p>\n<h3>Can I run a fish tank without a filter?</h3>\n<p>Technically yes \u2014 the Walstad method uses heavily planted tanks with rich substrate to process waste naturally. But for 99% of setups, a filter is essential. Without one, you'd need daily water changes to prevent toxic ammonia buildup.</p>\n<h3>HOB filter vs canister filter \u2014 which is better?</h3>\n<p>For tanks under 30 gallons, a quality HOB (like AquaClear) is perfectly adequate and easier to maintain. For 40+ gallons, canister filters provide superior filtration, more media capacity, and a cleaner look. If budget allows, canister is always the upgrade worth making.</p>\n<h3>What size filter do I need?</h3>\n<p>Choose a filter rated for 4\u20138\u00d7 your tank volume per hour. For a <a href=\"/tank-sizes/20-gallon-fish-tank\">20 gallon tank</a>, that's 80\u2013160 GPH. For messy fish like <a href=\"/fish/goldfish\">goldfish</a> or <a href=\"/fish/oscar-fish\">oscars</a>, go with 8\u201310\u00d7 turnover.</p>\n<h3>Do I need a filter for a shrimp tank?</h3>\n<p>Yes, but use a sponge filter \u2014 HOB and canister intakes can suck in baby <a href=\"/fish/cherry-shrimp\">shrimp</a>. If using a HOB or canister, cover the intake with a pre-filter sponge.</p>",
    "buyersGuide": "",
    "faq": [
      {
        "question": "How often should I clean my aquarium filter?",
        "answer": "Rinse mechanical media every 2-4 weeks in old tank water. Biological media only every 3-6 months. Never clean everything at once."
      },
      {
        "question": "What size filter do I need?",
        "answer": "Choose a filter rated for 4-8x your tank volume per hour. For messy fish like goldfish or oscars, aim for 8-10x turnover."
      },
      {
        "question": "HOB filter vs canister filter - which is better?",
        "answer": "HOB for tanks under 30 gallons (easier maintenance). Canister for 40+ gallons (superior filtration, cleaner look). Canister is always the upgrade worth making if budget allows."
      },
      {
        "question": "Do I need a filter for a shrimp tank?",
        "answer": "Yes - use a sponge filter for safety. HOB and canister intakes can suck in baby shrimp unless covered with a pre-filter sponge."
      },
      {
        "question": "Can I run a fish tank without a filter?",
        "answer": "The Walstad method uses heavy planting instead of filtration, but for 99% of setups a filter is essential. Without one, you'd need daily water changes."
      }
    ],
    "metaTitle": "Best Aquarium Filters 2025: HOB, Canister & Sponge Compared | World of Aquariums",
    "metaDescription": "Complete aquarium filter guide. Best HOB, canister, and sponge filters by tank size. AquaClear, Fluval, and budget picks with buyer's guide and filter media explained.",
    "keywords": [
      "aquarium filter",
      "best aquarium filter",
      "fish tank filter",
      "canister filter",
      "sponge filter",
      "hob filter",
      "aquarium filtration",
      "best filter for 10 gallon tank",
      "best filter for 20 gallon tank"
    ],
    "publishedAt": "2025-03-01",
    "updatedAt": "2025-03-10"
  },
  {
    "slug": "heaters",
    "title": "Best Aquarium Heaters in 2025: Sizing Guide & Reviews",
    "category": "heater",
    "products": [
      {
        "slug": "eheim-jager-100w",
        "name": "Eheim Jager 100W (Adjustable)",
        "brand": "Eheim",
        "category": "heater",
        "subcategory": "submersible",
        "price": {
          "min": 25,
          "max": 35
        },
        "rating": 4.7,
        "tankSizeRange": {
          "min": 15,
          "max": 40
        },
        "pros": [
          "TruTemp dial for precise temperature",
          "Fully submersible",
          "Thermo Safety Control auto-shutoff",
          "Accurate to \u00b10.5\u00b0F",
          "Proven reliability over decades",
          "Available in every wattage"
        ],
        "cons": [
          "Glass body (breakable if dropped)",
          "Suction cups weaken over time",
          "Indicator light can be hard to see"
        ],
        "bestFor": "Best overall adjustable heater for 15\u201340 gallon tanks",
        "affiliateUrl": "",
        "imageUrl": "/images/equipment/placeholder.jpg",
        "description": "The Eheim Jager has been the industry standard aquarium heater for decades. Its TruTemp dial allows precise temperature adjustment, the fully submersible glass body with thermal safety shutoff prevents overheating, and it's been proven reliable across millions of aquariums worldwide. Available from 25W to 300W to cover any tank size.",
        "metaTitle": "Eheim Jager Review",
        "metaDescription": "Eheim Jager adjustable aquarium heater review."
      },
      {
        "slug": "cobalt-neotherm-50w",
        "name": "Cobalt Aquatics Neo-Therm 50W",
        "brand": "Cobalt Aquatics",
        "category": "heater",
        "subcategory": "submersible",
        "price": {
          "min": 35,
          "max": 45
        },
        "rating": 4.6,
        "tankSizeRange": {
          "min": 5,
          "max": 15
        },
        "pros": [
          "Ultra-slim flat design",
          "LED temperature display",
          "One-touch controls",
          "Virtually unbreakable (not glass)",
          "Auto-shutoff protection",
          "Modern, sleek appearance"
        ],
        "cons": [
          "Premium price",
          "No external controller",
          "Suction cup mounting only"
        ],
        "bestFor": "Best looking heater for nano and small tanks where aesthetics matter",
        "affiliateUrl": "",
        "imageUrl": "/images/equipment/placeholder.jpg",
        "description": "The Cobalt Neo-Therm is the most visually appealing aquarium heater on the market. Its flat, slim profile with an integrated LED display looks more like a piece of modern tech than traditional glass tube heaters. The electronic thermostat is accurate and the one-touch controls are intuitive. Popular with aquascapers who want minimal visual intrusion.",
        "metaTitle": "Cobalt Neo-Therm Review",
        "metaDescription": "Cobalt Neo-Therm aquarium heater review."
      },
      {
        "slug": "fluval-e200",
        "name": "Fluval E200 Electronic Heater",
        "brand": "Fluval",
        "category": "heater",
        "subcategory": "submersible",
        "price": {
          "min": 45,
          "max": 60
        },
        "rating": 4.5,
        "tankSizeRange": {
          "min": 40,
          "max": 65
        },
        "pros": [
          "Real-time LCD temperature display",
          "Color-coded alerts (blue=cold, red=hot, green=correct)",
          "Dual temperature sensors",
          "Fish guard included",
          "Accurate electronic thermostat"
        ],
        "cons": [
          "Larger body than traditional heaters",
          "LCD can fail after several years",
          "Premium price for the wattage"
        ],
        "bestFor": "Best premium heater for 40\u201365 gallon tanks with temperature monitoring",
        "affiliateUrl": "",
        "imageUrl": "/images/equipment/placeholder.jpg",
        "description": "The Fluval E-series heaters feature a real-time LCD temperature display that changes color to indicate water temperature status \u2014 blue when heating, green when at target, red if overheating. The dual-sensor system and electronic thermostat provide excellent accuracy, and the included fish guard prevents burns.",
        "metaTitle": "Fluval E200 Review",
        "metaDescription": "Fluval E200 electronic aquarium heater review."
      },
      {
        "slug": "fluval-m25-nano",
        "name": "Fluval M25 Submersible Heater",
        "brand": "Fluval",
        "category": "heater",
        "subcategory": "submersible",
        "price": {
          "min": 12,
          "max": 18
        },
        "rating": 4.3,
        "tankSizeRange": {
          "min": 3,
          "max": 6
        },
        "pros": [
          "Very small and discreet",
          "Affordable",
          "Mirrors in-tank temperature accurately",
          "Good for nano tanks"
        ],
        "cons": [
          "Preset temperature (not adjustable)",
          "Limited to very small tanks",
          "No indicator light on some models"
        ],
        "bestFor": "Best budget nano heater for 3\u20136 gallon betta tanks",
        "affiliateUrl": "",
        "imageUrl": "/images/equipment/placeholder.jpg",
        "description": "The Fluval M25 is a compact, preset heater designed specifically for nano tanks. At just a few inches long, it fits discreetly in 3\u20136 gallon tanks and maintains water at approximately 78\u00b0F \u2014 ideal for bettas. While not adjustable, its set-and-forget simplicity makes it perfect for beginners with small tanks.",
        "metaTitle": "Fluval M25 Nano Heater Review",
        "metaDescription": "Fluval M25 nano aquarium heater review."
      },
      {
        "slug": "eheim-jager-300w",
        "name": "Eheim Jager 300W (Large Tanks)",
        "brand": "Eheim",
        "category": "heater",
        "subcategory": "submersible",
        "price": {
          "min": 35,
          "max": 50
        },
        "rating": 4.7,
        "tankSizeRange": {
          "min": 55,
          "max": 125
        },
        "pros": [
          "Same proven reliability as smaller Jagers",
          "Adequate for large tanks in most climates",
          "Precise TruTemp dial",
          "Thermal shutoff safety",
          "Great value for the wattage"
        ],
        "cons": [
          "Long glass body (14+ inches)",
          "Single unit may not heat evenly in 6-foot tanks",
          "Dual heater setup recommended for critical setups"
        ],
        "bestFor": "Best value heater for 55\u2013125 gallon tanks",
        "affiliateUrl": "",
        "imageUrl": "/images/equipment/placeholder.jpg",
        "description": "The 300W version of the legendary Eheim Jager brings the same reliability and precision to large aquariums. For tanks 55\u2013125 gallons, it provides adequate heating in most home environments. For tanks over 75 gallons or in cool rooms, pairing two 150W Jagers on opposite ends provides better heat distribution and failsafe redundancy.",
        "metaTitle": "Eheim Jager 300W Review",
        "metaDescription": "Eheim Jager 300W aquarium heater review for large tanks."
      }
    ],
    "introduction": "<h2 id=\"why-heaters-matter\">Why Aquarium Heaters Are Essential</h2>\n<p>Most popular aquarium fish are tropical species \u2014 <a href=\"/fish/betta-fish\">bettas</a>, <a href=\"/fish/neon-tetra\">tetras</a>, <a href=\"/fish/guppy\">guppies</a>, <a href=\"/fish/corydoras-catfish\">corydoras</a>, <a href=\"/fish/angelfish\">angelfish</a> \u2014 that need water temperatures between 75\u201382\u00b0F (24\u201328\u00b0C). Average room temperature (68\u201372\u00b0F) is too cold for these fish, weakening their immune systems, slowing metabolism, and eventually killing them.</p>\n<p>The exceptions: <a href=\"/fish/goldfish\">goldfish</a> are coldwater fish that don't need heaters, and <a href=\"/fish/axolotl\">axolotls</a> actually need cooler water (60\u201368\u00b0F). For everything else in the tropical freshwater hobby, a heater is essential equipment.</p>\n\n<h2 id=\"heater-sizing\">Heater Sizing Guide: How Many Watts Do You Need?</h2>\n<p>The general rule is <strong>3\u20135 watts per gallon</strong> of tank volume. However, the actual wattage needed depends on the temperature difference between your room and the target water temperature:</p>\n<ul>\n<li><strong><a href=\"/tank-sizes/5-gallon-fish-tank\">5 gallon tank</a>:</strong> 25\u201350W</li>\n<li><strong><a href=\"/tank-sizes/10-gallon-fish-tank\">10 gallon tank</a>:</strong> 50W</li>\n<li><strong><a href=\"/tank-sizes/15-gallon-fish-tank\">15 gallon tank</a>:</strong> 50\u201375W</li>\n<li><strong><a href=\"/tank-sizes/20-gallon-fish-tank\">20 gallon tank</a>:</strong> 75\u2013100W</li>\n<li><strong><a href=\"/tank-sizes/29-gallon-fish-tank\">29 gallon tank</a>:</strong> 100\u2013150W</li>\n<li><strong><a href=\"/tank-sizes/40-gallon-fish-tank\">40 gallon tank</a>:</strong> 150\u2013200W</li>\n<li><strong><a href=\"/tank-sizes/55-gallon-fish-tank\">55 gallon tank</a>:</strong> 200\u2013300W</li>\n<li><strong><a href=\"/tank-sizes/75-gallon-fish-tank\">75 gallon tank</a>:</strong> 250\u2013300W (or dual 150W)</li>\n<li><strong><a href=\"/tank-sizes/125-gallon-fish-tank\">125 gallon tank</a>:</strong> Two 200\u2013300W heaters</li>\n</ul>\n<p>In cooler rooms (below 65\u00b0F), go with the higher wattage. In consistently warm rooms (above 75\u00b0F), the lower end is fine. When in doubt, size up \u2014 a larger heater cycles on less frequently and works less hard, extending its lifespan.</p>\n\n<h2 id=\"dual-heater\">The Dual-Heater Strategy (40+ Gallons)</h2>\n<p>For tanks <a href=\"/tank-sizes/40-gallon-fish-tank\">40 gallons</a> and above, many experienced aquarists use <strong>two smaller heaters instead of one large one</strong>. For example, two 100W heaters instead of one 200W. Here's why:</p>\n<ul>\n<li><strong>Even heating:</strong> Two heaters on opposite ends of the tank distribute heat more evenly across the full length \u2014 critical for <a href=\"/tank-sizes/55-gallon-fish-tank\">4-foot tanks</a> and longer.</li>\n<li><strong>Redundancy:</strong> If one heater fails, the other prevents a catastrophic temperature crash. A single heater failure in winter can kill an entire tank overnight.</li>\n<li><strong>Overheat protection:</strong> If one heater's thermostat sticks \"on\" (the most dangerous heater failure), a single smaller heater may not be powerful enough to cook the tank before you notice.</li>\n</ul>\n<p>The dual-heater approach costs slightly more upfront but provides significant peace of mind for valuable fish collections.</p>\n\n<h2 id=\"heater-types\">Types of Aquarium Heaters</h2>\n<h3>Adjustable Submersible Heaters</h3>\n<p>The most common and recommended type. A glass or plastic tube with an adjustable thermostat dial, fully submerged in the tank. The Eheim Jager and Cobalt Neo-Therm are the industry leaders. Always choose adjustable over preset \u2014 you need the ability to raise temperature during <a href=\"/diseases\">disease treatment</a> (e.g., treating ich at 82\u201386\u00b0F).</p>\n\n<h3>Preset Heaters</h3>\n<p>Pre-set to a fixed temperature (usually 78\u00b0F). Simpler but less flexible. Acceptable for basic <a href=\"/fish/betta-fish\">betta tanks</a> but not recommended for community tanks or disease treatment situations.</p>\n\n<h3>Inline Heaters (Canister Filter Integration)</h3>\n<p>Install between canister filter hoses \u2014 water passes through the heater as it's pumped, heating it before returning to the tank. Advantages: completely invisible in the tank. Disadvantages: only works with canister filters, more expensive.</p>\n\n<h3>Substrate/Under-Tank Heaters</h3>\n<p>Heating cables or pads placed under or in the substrate. Used primarily in advanced planted tanks to create gentle convection currents through the substrate, promoting <a href=\"/plants\">plant root growth</a>. Not practical as primary heaters for most setups.</p>\n\n<h2 id=\"heater-placement\">Where to Place Your Heater</h2>\n<ul>\n<li><strong>Near water flow:</strong> Place near the <a href=\"/equipment/filters\">filter</a> intake or output to distribute heated water throughout the tank.</li>\n<li><strong>Fully submerged:</strong> Submersible heaters must be completely underwater. Exposing the heating element to air can cause cracking or overheating.</li>\n<li><strong>Vertical or angled:</strong> Position vertically or at a 45\u00b0 angle for best heat distribution and accurate thermostat reading.</li>\n<li><strong>With a thermometer:</strong> Always verify heater accuracy with a separate thermometer placed at the opposite end of the tank from the heater.</li>\n</ul>\n\n<h2 id=\"betta-heaters\">Best Heaters for Betta Fish</h2>\n<p><a href=\"/fish/betta-fish\">Bettas</a> need 76\u201382\u00b0F water, making a heater essential for any <a href=\"/tank-sizes/5-gallon-fish-tank\">5 gallon</a> betta tank. The best options:</p>\n<ul>\n<li><strong>Fluval M25:</strong> Compact preset heater, perfect for 5 gallon tanks. Set-and-forget simplicity.</li>\n<li><strong>Cobalt Neo-Therm 25W:</strong> Premium adjustable option with sleek design. Best if you want precise control.</li>\n<li><strong>Eheim Jager 25W:</strong> Budget-friendly adjustable. Reliable but the glass body looks large in a small tank.</li>\n</ul>\n<p>For <a href=\"/tank-sizes/3-gallon-fish-tank\">3 gallon</a> betta tanks, the Fluval P10 or a 10W preset heater works. Avoid overpowered heaters in nano tanks \u2014 they can swing temperature too rapidly.</p>\n\n<h2 id=\"common-problems\">Common Heater Problems & Solutions</h2>\n<ul>\n<li><strong>Heater stuck on (overheating):</strong> The most dangerous failure. Water temperature climbs uncontrollably. Solution: always use a separate thermostat/controller for critical setups, and the dual-heater strategy limits damage if one fails.</li>\n<li><strong>Heater not reaching target temperature:</strong> Usually undersized. Check your wattage against the sizing guide above. Also check room temperature \u2014 if your room drops below 60\u00b0F, you may need to size up.</li>\n<li><strong>Temperature fluctuations:</strong> Heater may be too close to the thermostat probe, or the tank is in a drafty area. Move heater near filter flow for better distribution. Avoid placing tanks near windows or heating/AC vents.</li>\n<li><strong>Cracked glass heater:</strong> Never plug in a heater that's not submerged. If you see cracks, replace immediately \u2014 water + electricity = danger.</li>\n<li><strong>Suction cups failing:</strong> Replace suction cups periodically (they harden over time). Some aquarists use heater holders or inline heaters to avoid this issue entirely.</li>\n</ul>\n\n<h2 id=\"faq\">Frequently Asked Questions</h2>\n<h3>Do betta fish need a heater?</h3>\n<p>Yes \u2014 <a href=\"/fish/betta-fish\">bettas</a> are tropical fish that need 76\u201382\u00b0F water. Room temperature water (68\u201372\u00b0F) weakens their immune system and shortens their lifespan. A heater is essential for any betta tank.</p>\n<h3>Do goldfish need a heater?</h3>\n<p>No \u2014 <a href=\"/fish/goldfish\">goldfish</a> are coldwater fish that prefer 65\u201375\u00b0F. They don't need a heater unless your home regularly drops below 60\u00b0F.</p>\n<h3>How many watts per gallon for an aquarium heater?</h3>\n<p>The general guideline is 3\u20135 watts per gallon. In cooler rooms, go higher (5W/gal). In warm rooms, the lower end (3W/gal) is sufficient. For tanks over 40 gallons, consider two heaters for even distribution.</p>\n<h3>Can a heater be too big for a fish tank?</h3>\n<p>A slightly oversized heater is actually fine \u2014 it cycles on less frequently and works less hard. However, a massively oversized heater (e.g., 300W in a 10 gallon) can overshoot temperature if the thermostat fails. Stick within 2\u00d7 the recommended wattage as a maximum.</p>\n<h3>Where should I place my aquarium heater?</h3>\n<p>Near the filter intake or outflow for best heat distribution. Fully submerged, positioned vertically or at a 45\u00b0 angle. Always verify with a separate thermometer on the opposite end of the tank.</p>",
    "buyersGuide": "",
    "faq": [
      {
        "question": "Do betta fish need a heater?",
        "answer": "Yes. Bettas are tropical fish that need 76-82\u00b0F water. Room temperature is too cold and weakens their immune system."
      },
      {
        "question": "How many watts per gallon for an aquarium heater?",
        "answer": "3-5 watts per gallon is the general guideline. In cooler rooms use 5W/gal, in warm rooms 3W/gal is fine."
      },
      {
        "question": "Do goldfish need a heater?",
        "answer": "No. Goldfish are coldwater fish that prefer 65-75\u00b0F. No heater needed unless your home drops below 60\u00b0F."
      },
      {
        "question": "Where should I place my aquarium heater?",
        "answer": "Near filter flow for heat distribution, fully submerged, vertical or 45\u00b0 angle. Always verify with a separate thermometer."
      },
      {
        "question": "Can a heater be too big for a fish tank?",
        "answer": "A slightly oversized heater is fine (less cycling, less wear). But don't exceed 2x the recommended wattage to limit damage if the thermostat fails."
      }
    ],
    "metaTitle": "Best Aquarium Heaters 2025: Sizing Guide & Reviews by Tank Size | World of Aquariums",
    "metaDescription": "Complete aquarium heater guide. Best heaters for every tank size (5-125 gal). Sizing calculator, dual-heater strategy, betta heaters, and product reviews.",
    "keywords": [
      "aquarium heater",
      "best aquarium heater",
      "fish tank heater",
      "betta fish heater",
      "heater for fish tank",
      "aquarium heater size",
      "watts per gallon heater"
    ],
    "publishedAt": "2025-03-01",
    "updatedAt": "2025-03-10"
  }
]